inql/__init__.py
inql/__main__.py
inql/__version__.py
inql/burp_loader.py
inql/constants.py
inql/cycles.py
inql/introspection.py
inql/utils.py
inql/actions/__init__.py
inql/actions/browser.py
inql/actions/executor.py
inql/actions/sendto.py
inql/actions/setcustomheader.py
inql/generators/__init__.py
inql/generators/cycles.py
inql/generators/html.py
inql/generators/query.py
inql/generators/schema.py
inql/generators/tsv.py
inql/widgets/__init__.py
inql/widgets/filetree.py
inql/widgets/fileview.py
inql/widgets/generator.py
inql/widgets/omnibar.py
inql/widgets/payloadview.py
inql/widgets/propertyeditor.py
inql/widgets/timer.py
inql-4.0.5.data/scripts/inql
inql-4.0.5.dist-info/LICENSE
inql-4.0.5.dist-info/METADATA
inql-4.0.5.dist-info/WHEEL
inql-4.0.5.dist-info/top_level.txt
inql-4.0.5.dist-info/RECORD
