Metadata-Version: 2.1
Name: inql
Version: 4.0.5
Summary: Pentesting tool for GraphQL triage
Home-page: UNKNOWN
Author: Andrea Brancaleoni
Author-email: andrea@doyensec.com
License: UNKNOWN
Platform: UNKNOWN
